cli.py
deepliif/__init__.py
deepliif/postprocessing.py
deepliif/data/__init__.py
deepliif/data/aligned_dataset.py
deepliif/data/base_dataset.py
deepliif/data/colorization_dataset.py
deepliif/data/image_folder.py
deepliif/data/single_dataset.py
deepliif/data/template_dataset.py
deepliif/data/unaligned_dataset.py
deepliif/models/CycleGAN_model.py
deepliif/models/DeepLIIFExt_model.py
deepliif/models/DeepLIIFKD_model.py
deepliif/models/DeepLIIF_model.py
deepliif/models/SDG_model.py
deepliif/models/__init__.py
deepliif/models/att_unet.py
deepliif/models/base_model.py
deepliif/models/networks.py
deepliif/options/__init__.py
deepliif/options/base_options.py
deepliif/options/processing_options.py
deepliif/options/test_options.py
deepliif/options/train_options.py
deepliif/util/__init__.py
deepliif/util/checks.py
deepliif/util/get_data.py
deepliif/util/html.py
deepliif/util/image_pool.py
deepliif/util/util.py
deepliif/util/visualizer.py
deepliif-1.2.4.dist-info/LICENSE.md
deepliif-1.2.4.dist-info/METADATA
deepliif-1.2.4.dist-info/WHEEL
deepliif-1.2.4.dist-info/entry_points.txt
deepliif-1.2.4.dist-info/top_level.txt
deepliif-1.2.4.dist-info/RECORD
