Metadata-Version: 2.1
Name: deepliif
Version: 1.2.4
Summary: DeepLIIF: Deep-Learning Inferred Multiplex Immunofluorescence for Immunohistochemical Image Quantification
Home-page: https://github.com/nadeemlab/DeepLIIF
Author: Parmida93
Author-email: ghahremani.parmida@gmail.com
Keywords: DeepLIIF,IHC,Segmentation,Classification
License-File: LICENSE.md
Requires-Dist: opencv-python (==4.8.1.78)
Requires-Dist: torch (==2.8.0)
Requires-Dist: torchvision (>=0.14.1)
Requires-Dist: scikit-image (==0.18.3)
Requires-Dist: dominate (==2.6.0)
Requires-Dist: numba (==0.57.1)
Requires-Dist: Click (==8.0.3)
Requires-Dist: requests (==2.32.2)
Requires-Dist: dask (==2021.11.2)
Requires-Dist: visdom (>=0.1.8.3)
Requires-Dist: python-bioformats (>=4.0.6)
Requires-Dist: imagecodecs (==2023.3.16)
Requires-Dist: zarr (==2.16.1)
